{"title":"Body","body":{"content":{"application/json":{"schema":{"type":"object","properties":{"keys":{"type":"array","items":{"type":"object","properties":{"branch":{"type":"string"},"name":{"type":"string","description":"Key name to set translations for","example":"what_a_key_to_translate","minLength":1},"namespace":{"type":"string","description":"The namespace of the key. (When empty or null default namespace will be used)"},"screenshots":{"type":"array","items":{"type":"object","properties":{"positions":{"type":"array","items":{"type":"object","properties":{"height":{"type":"integer","format":"int32"},"width":{"type":"integer","format":"int32"},"x":{"type":"integer","format":"int32"},"y":{"type":"integer","format":"int32"}},"required":["height","width","x","y"],"title":"KeyInScreenshotPositionDto"}},"text":{"type":"string"},"uploadedImageId":{"type":"integer","format":"int64","description":"Ids of screenshot uploaded with /v2/image-upload endpoint"}},"required":["uploadedImageId"],"title":"KeyScreenshotDto"}},"translations":{"type":"object","additionalProperties":{"type":"object","properties":{"resolution":{"type":"string","description":"Determines, how conflict is resolved.\n      - KEEP: Translation is not changed\n      - OVERRIDE: Translation is overridden\n      - NEW: New translation is created\n      - FORCE_OVERRIDE: Translation is updated, created or kept.\n    ","enum":["KEEP","OVERRIDE","NEW","FORCE_OVERRIDE"],"example":"OVERRIDE"},"text":{"type":"string","description":"Translation text","example":"Hello! I am a translation!"}},"required":["resolution","text"],"title":"ImportTranslationResolvableDto"},"description":"Object mapping language tag to translation"}},"required":["name","translations"],"title":"ImportKeysResolvableItemDto"}}},"required":["keys"],"title":"ImportKeysResolvableDto"}}},"required":true}}